{
  "required": true,
  "minVersion": "0.8",
  "package": "net.ranold.mixin",
  "plugin": "net.ranold.SSRDMixinPlugin",
  "compatibilityLevel": "JAVA_21",
  "mixins": [
    "SubLevelTrackingSystemMixin",
    "SubLevelHoldingChunkMapMixin",
    "EntityTypeMixin",
    "ChunkMapMixin",
    "ServerLevelMixin",
    "ChunkMapTrackedEntityMixin"
  ],
  "client": [
    "RenderSectionManagerMixin",
    "SodiumGameOptionPagesMixin",
    "OptionPageAccessor",
    "OptionGroupAccessor",
    "SubLevelRenderSectionManagerMixin",
    "VanillaFrustumMixin",
    "OcclusionCullerMixin",
    "SodiumDispatcherMixin",
    "SodiumViewportMixin",
    "RenderSystemFogMixin",
    "LevelRendererMixin",
    "MinecraftLoadingMixin",
    "VanillaDispatcherMixin",
    "GameRendererProjMixin",
    "DHShaderSourceMixin",
    "DHRenderUtilProjMixin",
    "EntityRenderDispatcherMixin",
    "BlockEntityRendererMixin",
    "AbstractContraptionEntityMixin",
    "AbstractEntityVisualMixin",
    "AbstractBlockEntityVisualMixin",
    "ClientLevelMixin",
    "BandedPrimeLimiterMixin",
    "FrameUniformsMixin"
  ],
  "server": [
  ],
  "injectors": {
    "defaultRequire": 1
  }
}
